deeptest_cli/config.py
deeptest_cli/main.py
deeptest_cli/commands/login.py
deeptest_cli/commands/runner.py
deeptest_cli/commands/validate.py
deeptest_cli/lib/auth.py
deeptest_cli/lib/models.py
deeptest_cli/lib/yaml.py
deeptest_cli-0.0.5.dist-info/METADATA
deeptest_cli-0.0.5.dist-info/WHEEL
deeptest_cli-0.0.5.dist-info/entry_points.txt
deeptest_cli-0.0.5.dist-info/RECORD
